{
  "tuning": "TODO",
  "artist": "Toprak Barut",
  "title": "Major_Scale(1)",
  "metre": "4/4",
  "sandbox": {
   "path": "$JAZZ_HARMONY_DATA_ROOT//Tracks/scales_dataset/toprak_major1.aiff",
   "transcriptions": ["Emir Demirel"],
   "key":["Bb"]
  },
  "duration": "TODO",
  "parts":
          [
            {
              "name":"Part1",
              "startTime":"0",
              "endTime":"11.68",
              "scaleType": "Bb:major"
            },
            {
              "name":"Part2",
              "startTime":"11.99",
              "endTime":"17.15",
              "scaleType": "Bb:major"
            },
            {
              "name":"Part3",
              "startTime":"17.27",
              "endTime":"30.959",
              "scaleType": "Bb:major"
            },
            {
              "name":"Part4",
              "startTime":"31.24",
              "endTime":"42.92",
              "scaleType": "Bb:major"
            },
            {
              "name":"Part5",
              "startTime":"45.73",
              "endTime":"51.859",
              "scaleType": "Bb:major"
            }
          ]

}